CHANGES.txt
LICENSE.GPL
LICENSE.txt
MANIFEST.in
README.rst
setup.py
leocornus/__init__.py
leocornus.py.sandbox.egg-info/PKG-INFO
leocornus.py.sandbox.egg-info/SOURCES.txt
leocornus.py.sandbox.egg-info/dependency_links.txt
leocornus.py.sandbox.egg-info/entry_points.txt
leocornus.py.sandbox.egg-info/namespace_packages.txt
leocornus.py.sandbox.egg-info/not-zip-safe
leocornus.py.sandbox.egg-info/requires.txt
leocornus.py.sandbox.egg-info/top_level.txt
leocornus/py/__init__.py
leocornus/py/sandbox/README.rst
leocornus/py/sandbox/__init__.py
leocornus/py/sandbox/utils_basic.py
leocornus/py/sandbox/utils_mwclient.py
leocornus/py/sandbox/tests/__init__.py
leocornus/py/sandbox/tests/basicPython.rst
leocornus/py/sandbox/tests/codeConvention.rst
leocornus/py/sandbox/tests/pprintStory.rst
leocornus/py/sandbox/tests/searchArchiveStory.rst
leocornus/py/sandbox/tests/testDoctests.py
leocornus/py/sandbox/tests/class/basic.rst
leocornus/py/sandbox/tests/config/configParserStory.rst
leocornus/py/sandbox/tests/core/README.rst
leocornus/py/sandbox/tests/core/builtinFunctions.rst
leocornus/py/sandbox/tests/core/builtinTypes.rst
leocornus/py/sandbox/tests/core/fileReadWrite.rst
leocornus/py/sandbox/tests/core/popenTips.rst
leocornus/py/sandbox/tests/core/shlexTips.rst
leocornus/py/sandbox/tests/core/subprocessTips.rst
leocornus/py/sandbox/tests/eve/README.rst
leocornus/py/sandbox/tests/eve/eveGetStarted.rst
leocornus/py/sandbox/tests/fabric/README.rst
leocornus/py/sandbox/tests/fabric/basicLocalFabric.rst
leocornus/py/sandbox/tests/fabric/fabric-git.rst
leocornus/py/sandbox/tests/mwclient/README.rst
leocornus/py/sandbox/tests/mwclient/mwclientBasic.rst
leocornus/py/sandbox/tests/mwclient/testMwrcSite.rst
leocornus/py/sandbox/tests/mwclient/wpFileHeader2mw.rst
leocornus/py/sandbox/tests/pexpect/nodejsStory.rst
leocornus/py/sandbox/tests/pexpect/pexpectBasic.rst
leocornus/py/sandbox/tests/regexp/README.rst
leocornus/py/sandbox/tests/regexp/reModuleBasic.rst
leocornus/py/sandbox/tests/sqlalchemy/README.rst
leocornus/py/sandbox/tests/sqlite/README.rst
leocornus/py/sandbox/tests/sqlite/basicSqlite3.rst