Metadata-Version: 1.1
Name: leocornus.py.sandbox
Version: 1.0.7
Summary: Play ground for learning Python language
Home-page: http://github.com/leocornus/leocornus.py.sandbox
Author: Sean Chen
Author-email: sean.chen@leocorn.com
License: GPLv2
Keywords: development sandbox learning
Platform: UNKNOWN
Classifier: Intended Audience :: Developers
Classifier: License :: OSI Approved :: GNU General Public License (GPL)
Classifier: Topic :: Software Development :: Testing
Classifier: Topic :: Software Development :: Documentation
Classifier: Topic :: Software Development :: Libraries :: Python Modules
